pylaroid/__init__.py
pylaroid/console_script.py
pylaroid/file_handler.py
pylaroid/models.py
pylaroid/pdf.py
pylaroid/polaroid.py
pylaroid-0.0.7.dist-info/DESCRIPTION.rst
pylaroid-0.0.7.dist-info/METADATA
pylaroid-0.0.7.dist-info/RECORD
pylaroid-0.0.7.dist-info/WHEEL
pylaroid-0.0.7.dist-info/entry_points.txt
pylaroid-0.0.7.dist-info/metadata.json
pylaroid-0.0.7.dist-info/top_level.txt
pylaroid-0.0.7.dist-info/zip-safe
