Metadata-Version: 2.0
Name: pylaroid
Version: 0.0.7
Summary: Fake self-developing film generator
Home-page: UNKNOWN
Author: Philippe Lafaye
Author-email: rage2000@gmail.com
License: UNKNOWN
Platform: UNKNOWN
Provides-Extra: dev
Requires-Dist: argh
Requires-Dist: click
Requires-Dist: pathtools
Requires-Dist: pillow
Requires-Dist: reportlab
Requires-Dist: wand
Requires-Dist: watchdog
Provides-Extra: dev
Requires-Dist: flake8; extra == 'dev'
Requires-Dist: pytest; extra == 'dev'
Requires-Dist: sphinx; extra == 'dev'
Requires-Dist: sphinx-rtd-theme; extra == 'dev'
Requires-Dist: sphinx-autobuild; extra == 'dev'
